{
  "status": "Ongoing",
  "year": "Ongoing",
  "date": "Ongoing",
  "amount": "RM 50,000,000.00",
  "client": "Kementerian Kemajuan Desa Dan Wilayah (KKDW)",
  "description": "Membina Jalan Dari Bukit Jayong Belaga, Bahagian Kapit Ke Jalan Data Kakus, Tatau, Bahagian Bintulu Sarawak",
  "cat": "Infrastructure",
  "division": "Kapit",
  "loc": "Bukit Jayong, Belaga",
  "accuracy": "Approximate (Bukit Jayong, Belaga — road towards Jln Data Kakus, Tatau)",
  "images": [],
  "coordinates": "2.7, 113.783",
  "lat": 2.7,
  "lng": 113.783
}