{
  "status": "Siap",
  "year": "2016",
  "date": "10 Sep 2016",
  "amount": "RM 56,000.00",
  "client": "",
  "description": "Proposed Mobilization, Construction, Erection, Completion, Testing and Commissioning Of 30m Telecommunication Rapid Assembly Poles (\"Rapole\") And Other Related Infrastructure Works at Taman Permai (RMAI)(T1100280), Sibu.",
  "cat": "Telecom",
  "division": "Sibu",
  "loc": "Taman Permai, Sibu",
  "accuracy": "Approximate (Taman Permai, Sibu)",
  "paragraph": "This is a placeholder description that provides a brief overview of the project scope and key objectives. It will be updated by the administration at a later date to feature the actual narrative.",
  "images": [],
  "coordinates": "2.29, 111.83",
  "lat": 2.29,
  "lng": 111.83
}